MANIFEST.in
README.rst
setup.py
aliyun_python_sdk_vod_test.egg-info/PKG-INFO
aliyun_python_sdk_vod_test.egg-info/SOURCES.txt
aliyun_python_sdk_vod_test.egg-info/dependency_links.txt
aliyun_python_sdk_vod_test.egg-info/requires.txt
aliyun_python_sdk_vod_test.egg-info/top_level.txt
aliyunsdkvod/__init__.py
aliyunsdkvod/request/__init__.py
aliyunsdkvod/request/v20170321/AddAITemplateRequest.py
aliyunsdkvod/request/v20170321/AddCategoryRequest.py
aliyunsdkvod/request/v20170321/AddEditingProjectRequest.py
aliyunsdkvod/request/v20170321/AddTranscodeTemplateGroupRequest.py
aliyunsdkvod/request/v20170321/AddVodDomainRequest.py
aliyunsdkvod/request/v20170321/AddVodTemplateRequest.py
aliyunsdkvod/request/v20170321/AddWatermarkRequest.py
aliyunsdkvod/request/v20170321/AttachAppPolicyToIdentityRequest.py
aliyunsdkvod/request/v20170321/BatchSetVodDomainConfigsRequest.py
aliyunsdkvod/request/v20170321/BatchStartVodDomainRequest.py
aliyunsdkvod/request/v20170321/BatchStopVodDomainRequest.py
aliyunsdkvod/request/v20170321/CreateAppInfoRequest.py
aliyunsdkvod/request/v20170321/CreateAuditRequest.py
aliyunsdkvod/request/v20170321/CreateUploadAttachedMediaRequest.py
aliyunsdkvod/request/v20170321/CreateUploadImageRequest.py
aliyunsdkvod/request/v20170321/CreateUploadVideoRequest.py
aliyunsdkvod/request/v20170321/DeleteAITemplateRequest.py
aliyunsdkvod/request/v20170321/DeleteAppInfoRequest.py
aliyunsdkvod/request/v20170321/DeleteAttachedMediaRequest.py
aliyunsdkvod/request/v20170321/DeleteCategoryRequest.py
aliyunsdkvod/request/v20170321/DeleteEditingProjectRequest.py
aliyunsdkvod/request/v20170321/DeleteImageRequest.py
aliyunsdkvod/request/v20170321/DeleteMessageCallbackRequest.py
aliyunsdkvod/request/v20170321/DeleteMezzaninesRequest.py
aliyunsdkvod/request/v20170321/DeleteMultipartUploadRequest.py
aliyunsdkvod/request/v20170321/DeleteStreamRequest.py
aliyunsdkvod/request/v20170321/DeleteTranscodeTemplateGroupRequest.py
aliyunsdkvod/request/v20170321/DeleteVideoRequest.py
aliyunsdkvod/request/v20170321/DeleteVodDomainRequest.py
aliyunsdkvod/request/v20170321/DeleteVodSpecificConfigRequest.py
aliyunsdkvod/request/v20170321/DeleteVodTemplateRequest.py
aliyunsdkvod/request/v20170321/DeleteWatermarkRequest.py
